cb85/dec.cpython-38-x86_64-linux-gnu.so
cb85/test_enc.py
cb85/test_dec.py
cb85/__init__.py
cb85/enc.cpython-38-x86_64-linux-gnu.so
cb85-0.0.2.dist-info/RECORD
cb85-0.0.2.dist-info/WHEEL
cb85-0.0.2.dist-info/top_level.txt
cb85-0.0.2.dist-info/METADATA
cb85-0.0.2.dist-info/LICENSE
