Metadata-Version: 2.1
Name: cb85
Version: 0.0.2
Summary: Cythonized Base85 encoder and decoder.
Home-page: https://github.com/Chicoryn/cb85
Author: Karl Sundequist Blomdahl
Author-email: karl.sundequist.blomdahl@gmail.com
License: Apache-2.0
Platform: UNKNOWN
